{"errors":[],"warnings":[],"namedChunkGroups":{"polyfill":{"chunks":[2,14],"assets":["webpack-runtime-03a7de2084afb64b8fd0.js","webpack-runtime-03a7de2084afb64b8fd0.js.map","polyfill-d315eb99cbdcd89ab179.js","polyfill-d315eb99cbdcd89ab179.js.map"],"children":{},"childAssets":{}},"app":{"chunks":[2,13,6],"assets":["webpack-runtime-03a7de2084afb64b8fd0.js","webpack-runtime-03a7de2084afb64b8fd0.js.map","framework-29ba174b433dc5858bed.js","framework-29ba174b433dc5858bed.js.map","app-9fc861d3c766227d4ed0.js","app-9fc861d3c766227d4ed0.js.map"],"children":{},"childAssets":{}},"component---src-pages-404-js":{"chunks":[1,0,7],"assets":["styles.cd799e412af29cd479f8.css","styles-e9d24b1846c7d6eb9685.js","styles-e9d24b1846c7d6eb9685.js.map","commons-0c152b0333e51a0b04fb.js","commons-0c152b0333e51a0b04fb.js.map","component---src-pages-404-js-a1c5686f04c61c840a61.js","component---src-pages-404-js-a1c5686f04c61c840a61.js.map"],"children":{},"childAssets":{}},"component---src-pages-contact-js":{"chunks":[1,4,0,8],"assets":["styles.cd799e412af29cd479f8.css","styles-e9d24b1846c7d6eb9685.js","styles-e9d24b1846c7d6eb9685.js.map","31664189-251b66add8e0ecc98521.js","31664189-251b66add8e0ecc98521.js.map","commons-0c152b0333e51a0b04fb.js","commons-0c152b0333e51a0b04fb.js.map","component---src-pages-contact-js-6bff35e3c60ec08148f9.js","component---src-pages-contact-js-6bff35e3c60ec08148f9.js.map"],"children":{},"childAssets":{}},"component---src-pages-design-js":{"chunks":[1,5,3,0,9],"assets":["styles.cd799e412af29cd479f8.css","styles-e9d24b1846c7d6eb9685.js","styles-e9d24b1846c7d6eb9685.js.map","95b64a6e-838006e83605c62eb3b6.js","95b64a6e-838006e83605c62eb3b6.js.map","252f366e-fe7d56054f303c5e8549.js","252f366e-fe7d56054f303c5e8549.js.map","commons-0c152b0333e51a0b04fb.js","commons-0c152b0333e51a0b04fb.js.map","component---src-pages-design-js-d87713635b55d376398d.js","component---src-pages-design-js-d87713635b55d376398d.js.map"],"children":{},"childAssets":{}},"component---src-pages-index-js":{"chunks":[1,0,10],"assets":["styles.cd799e412af29cd479f8.css","styles-e9d24b1846c7d6eb9685.js","styles-e9d24b1846c7d6eb9685.js.map","commons-0c152b0333e51a0b04fb.js","commons-0c152b0333e51a0b04fb.js.map","component---src-pages-index-js-c24932eb73c731e97ffb.js","component---src-pages-index-js-c24932eb73c731e97ffb.js.map"],"children":{},"childAssets":{}},"component---src-pages-masterpiece-js":{"chunks":[1,0,11],"assets":["styles.cd799e412af29cd479f8.css","styles-e9d24b1846c7d6eb9685.js","styles-e9d24b1846c7d6eb9685.js.map","commons-0c152b0333e51a0b04fb.js","commons-0c152b0333e51a0b04fb.js.map","component---src-pages-masterpiece-js-e227bdd531e0546011cc.js","component---src-pages-masterpiece-js-e227bdd531e0546011cc.js.map"],"children":{},"childAssets":{}},"component---src-pages-skill-js":{"chunks":[1,0,12],"assets":["styles.cd799e412af29cd479f8.css","styles-e9d24b1846c7d6eb9685.js","styles-e9d24b1846c7d6eb9685.js.map","commons-0c152b0333e51a0b04fb.js","commons-0c152b0333e51a0b04fb.js.map","component---src-pages-skill-js-b517d085deb9a18082b1.js","component---src-pages-skill-js-b517d085deb9a18082b1.js.map"],"children":{},"childAssets":{}}},"assetsByChunkName":{"polyfill":["webpack-runtime-03a7de2084afb64b8fd0.js","polyfill-d315eb99cbdcd89ab179.js"],"app":["webpack-runtime-03a7de2084afb64b8fd0.js","framework-29ba174b433dc5858bed.js","app-9fc861d3c766227d4ed0.js"],"component---src-pages-404-js":["styles.cd799e412af29cd479f8.css","styles-e9d24b1846c7d6eb9685.js","commons-0c152b0333e51a0b04fb.js","component---src-pages-404-js-a1c5686f04c61c840a61.js"],"component---src-pages-contact-js":["styles.cd799e412af29cd479f8.css","styles-e9d24b1846c7d6eb9685.js","31664189-251b66add8e0ecc98521.js","commons-0c152b0333e51a0b04fb.js","component---src-pages-contact-js-6bff35e3c60ec08148f9.js"],"component---src-pages-design-js":["styles.cd799e412af29cd479f8.css","styles-e9d24b1846c7d6eb9685.js","95b64a6e-838006e83605c62eb3b6.js","252f366e-fe7d56054f303c5e8549.js","commons-0c152b0333e51a0b04fb.js","component---src-pages-design-js-d87713635b55d376398d.js"],"component---src-pages-index-js":["styles.cd799e412af29cd479f8.css","styles-e9d24b1846c7d6eb9685.js","commons-0c152b0333e51a0b04fb.js","component---src-pages-index-js-c24932eb73c731e97ffb.js"],"component---src-pages-masterpiece-js":["styles.cd799e412af29cd479f8.css","styles-e9d24b1846c7d6eb9685.js","commons-0c152b0333e51a0b04fb.js","component---src-pages-masterpiece-js-e227bdd531e0546011cc.js"],"component---src-pages-skill-js":["styles.cd799e412af29cd479f8.css","styles-e9d24b1846c7d6eb9685.js","commons-0c152b0333e51a0b04fb.js","component---src-pages-skill-js-b517d085deb9a18082b1.js"]}}